setup.py
obiwan/__init__.py
obiwan.egg-info/PKG-INFO
obiwan.egg-info/SOURCES.txt
obiwan.egg-info/dependency_links.txt
obiwan.egg-info/top_level.txt
test/test_doctest.py
test/test_templates.py