Metadata-Version: 1.0
Name: obiwan
Version: 1.0.7
Summary: A runtime type checker (contract system) and JSON validator
Home-page: https://github.com/williame/obiwan
Author: William Edwards
Author-email: willvarfar@gmail.com
License: UNKNOWN
Platform: UNKNOWN
